pyrfp/__init__.py
pyrfp/model_tools.py
pyrfp/simulator.py
pyrfp/training.py
pyrfp/training_data.py
pyrfp/training_model.py
pyrfp/training_runner.py
pyrfp/training_tools.py
pyrfp/types.py
pyrfp-0.1.2.dist-info/WHEEL
pyrfp-0.1.2.dist-info/METADATA
pyrfp-0.1.2.dist-info/RECORD
