Metadata-Version: 2.1
Name: pyrfp
Version: 0.1.2
Summary: Python package for the data-driven Rosenbluth-Fokker-Planck equation.
Author: Kyoungseoun Chung
Author-email: kyoungseoun.chung@gmail.com
Requires-Python: >=3.10,<3.12
Classifier: Programming Language :: Python :: 3
Classifier: Programming Language :: Python :: 3.10
Requires-Dist: pyapes (>=0.2.1,<0.3.0)
Requires-Dist: pymaxed (>=0.1.7,<0.2.0)
Requires-Dist: pymytools (>=0.1.12,<0.2.0)
